pcv/__init__.py
pcv/filters.py
pcv/start.py
pcv/defaults/makecv.py
pcv/defaults/settings.py
pcv/defaults/source/cv_template.json
pcv/defaults/source/template.json
pcv/templates/contact.html
pcv/templates/education.html
pcv/templates/experience.html
pcv/templates/languages.html
pcv/templates/motto.html
pcv/templates/onepage.html
pcv/templates/online.html
pcv/templates/pages.html
pcv/templates/person.html
pcv/templates/references.html
pcv/templates/section.html
pcv/templates/skills.html
pcv/templates/skills_short.html
pcv/templates/style_pages.css
pcv/templates/style_zero.css
pcv/templates/technologies.html
pcv/templates/pages/onepage.html
pcv/templates/pages/publications.html
pcv/templates/pages/technologies.html
pcv/templates/sections/contact.html
pcv/templates/sections/education.html
pcv/templates/sections/experience.html
pcv/templates/sections/languages.html
pcv/templates/sections/motto.html
pcv/templates/sections/online.html
pcv/templates/sections/person.html
pcv/templates/sections/references.html
pcv/templates/sections/section.html
pcv/templates/sections/skills.html
pcv/templates/sections/skills_short.html
pcv/templates/styles/style_pages.css
pcv/templates/styles/style_zero.css
pcv-0.0.2.dist-info/LICENSE
pcv-0.0.2.dist-info/METADATA
pcv-0.0.2.dist-info/WHEEL
pcv-0.0.2.dist-info/top_level.txt
pcv-0.0.2.dist-info/RECORD
