Metadata-Version: 2.1
Name: pcv
Version: 0.0.2
Summary: Build a crisp CV (resume), as printable HTML, from JSON.
Home-page: https://github.com/dennisvang/pcv/
Author: D. van Gerwen
Author-email: djvg@protonmail.com
License: UNKNOWN
Platform: UNKNOWN
Classifier: Programming Language :: Python :: 3
Classifier: License :: OSI Approved :: MIT License
Classifier: Operating System :: OS Independent
Requires-Python: >=3.8
Requires-Dist: jinja2
